StarkChat/__init__.py
StarkChat/aiml_data/alice/ai.aiml
StarkChat/aiml_data/alice/alice.aiml
StarkChat/aiml_data/alice/astrology.aiml
StarkChat/aiml_data/alice/atomic.aiml
StarkChat/aiml_data/alice/badanswer.aiml
StarkChat/aiml_data/alice/biography.aiml
StarkChat/aiml_data/alice/bot.aiml
StarkChat/aiml_data/alice/bot_profile.aiml
StarkChat/aiml_data/alice/client.aiml
StarkChat/aiml_data/alice/client_profile.aiml
StarkChat/aiml_data/alice/computers.aiml
StarkChat/aiml_data/alice/continuation.aiml
StarkChat/aiml_data/alice/copyme.aiml
StarkChat/aiml_data/alice/currency.aiml
StarkChat/aiml_data/alice/custom.aiml
StarkChat/aiml_data/alice/date.aiml
StarkChat/aiml_data/alice/def.aiml
StarkChat/aiml_data/alice/default.aiml
StarkChat/aiml_data/alice/drphil.aiml
StarkChat/aiml_data/alice/drugs.aiml
StarkChat/aiml_data/alice/emotion.aiml
StarkChat/aiml_data/alice/food.aiml
StarkChat/aiml_data/alice/geography.aiml
StarkChat/aiml_data/alice/gossip.aiml
StarkChat/aiml_data/alice/happy.aiml
StarkChat/aiml_data/alice/history.aiml
StarkChat/aiml_data/alice/humor.aiml
StarkChat/aiml_data/alice/imponderables.aiml
StarkChat/aiml_data/alice/inquiry.aiml
StarkChat/aiml_data/alice/interjection.aiml
StarkChat/aiml_data/alice/iu.aiml
StarkChat/aiml_data/alice/jokes.aiml
StarkChat/aiml_data/alice/knowledge.aiml
StarkChat/aiml_data/alice/literature.aiml
StarkChat/aiml_data/alice/loebner10.aiml
StarkChat/aiml_data/alice/money.aiml
StarkChat/aiml_data/alice/movies.aiml
StarkChat/aiml_data/alice/mp0.aiml
StarkChat/aiml_data/alice/mp1.aiml
StarkChat/aiml_data/alice/mp2.aiml
StarkChat/aiml_data/alice/mp3.aiml
StarkChat/aiml_data/alice/mp4.aiml
StarkChat/aiml_data/alice/mp5.aiml
StarkChat/aiml_data/alice/mp6.aiml
StarkChat/aiml_data/alice/music.aiml
StarkChat/aiml_data/alice/numbers.aiml
StarkChat/aiml_data/alice/personality.aiml
StarkChat/aiml_data/alice/phone.aiml
StarkChat/aiml_data/alice/pickup.aiml
StarkChat/aiml_data/alice/politics.aiml
StarkChat/aiml_data/alice/primeminister.aiml
starkchat-0.0.4.dist-info/LICENSE
starkchat-0.0.4.dist-info/WHEEL
starkchat-0.0.4.dist-info/METADATA
starkchat-0.0.4.dist-info/RECORD
